{
"tests/algorithm/linear_floor_sum.test.cpp": "2023-02-10 19:16:28 +0900",
"tests/algorithm/mo.test.cpp": "2023-02-06 14:16:07 +0900",
"tests/common/bit_op.test.cpp": "2022-08-14 03:13:41 +0900",
"tests/common/chminmax.test.cpp": "2022-08-14 03:13:41 +0900",
"tests/common/container_op.fillAll.test.cpp": "2023-02-06 14:16:07 +0900",
"tests/common/container_op.reverseAll.test.cpp": "2023-02-06 14:16:07 +0900",
"tests/common/container_op.sortAll.test.cpp": "2023-02-06 14:16:07 +0900",
"tests/common/container_op.sumAll.test.cpp": "2023-02-06 14:16:07 +0900",
"tests/common/container_op.test.cpp": "2023-02-06 14:16:07 +0900",
"tests/common/int_div.test.cpp": "2022-08-14 03:13:41 +0900",
"tests/common/irange.test.cpp": "2022-08-14 03:13:41 +0900",
"tests/common/powerInt.test.cpp": "2022-08-14 03:13:41 +0900",
"tests/common/powerMonoid.test.cpp": "2022-08-14 03:13:41 +0900",
"tests/convex_hull_trick/li_chao_tree.line.test.cpp": "2023-02-06 14:16:07 +0900",
"tests/convex_hull_trick/li_chao_tree.segment.test.cpp": "2023-02-06 14:16:07 +0900",
"tests/convex_hull_trick/monotone_cht.test.cpp": "2023-02-06 14:16:07 +0900",
"tests/data_structure/fenwick_tree/fenwick.max_right.test.cpp": "2023-02-06 14:16:07 +0900",
"tests/data_structure/fenwick_tree/fenwick.test.cpp": "2023-02-06 14:16:07 +0900",
"tests/data_structure/segment_tree/dual_segtree.test.cpp": "2023-02-06 14:16:07 +0900",
"tests/data_structure/segment_tree/lazy_segtree.test.cpp": "2023-02-06 14:16:07 +0900",
"tests/data_structure/segment_tree/segtree.test.cpp": "2023-02-06 14:16:07 +0900",
"tests/data_structure/segment_tree/segtree_beats.test.cpp": "2023-02-06 14:16:07 +0900",
"tests/data_structure/sliding_window_aggregation/deque.test.cpp": "2023-02-06 14:16:07 +0900",
"tests/data_structure/sliding_window_aggregation/queue.test.cpp": "2023-02-06 14:16:07 +0900",
"tests/data_structure/sparse_table/disjoint_sparse_table.rmq.test.cpp": "2023-02-06 14:16:07 +0900",
"tests/data_structure/sparse_table/static_rmq.rMq.test.cpp": "2023-02-06 14:16:07 +0900",
"tests/data_structure/sparse_table/static_rmq.rmq.test.cpp": "2023-02-06 14:16:07 +0900",
"tests/data_structure/union_find_tree/union_find_tree.test.cpp": "2023-02-06 14:16:07 +0900",
"tests/data_structure/wavelet/wavelet_matrix.quantile.test.cpp": "2023-02-06 14:16:07 +0900",
"tests/data_structure/wavelet/wavelet_matrix.rangefreq.test.cpp": "2023-02-06 14:16:07 +0900",
"tests/formal_dirichlet_series/gcd_convolution.test.cpp": "2023-02-06 14:16:07 +0900",
"tests/formal_dirichlet_series/lcm_convolution.test.cpp": "2023-02-06 14:16:07 +0900",
"tests/formal_power_series/berlekamp_massey.test.cpp": "2023-02-06 14:16:07 +0900",
"tests/formal_power_series/bostan_mori.test.cpp": "2023-02-06 14:16:07 +0900",
"tests/formal_power_series/formal_power_series.convolution.test.cpp": "2023-02-06 14:16:07 +0900",
"tests/formal_power_series/formal_power_series.convolution1000000007.test.cpp": "2023-02-06 14:16:07 +0900",
"tests/formal_power_series/formal_power_series.exp.test.cpp": "2023-02-06 14:16:07 +0900",
"tests/formal_power_series/formal_power_series.inv.test.cpp": "2023-02-06 14:16:07 +0900",
"tests/formal_power_series/formal_power_series.log.test.cpp": "2023-02-06 14:16:07 +0900",
"tests/formal_power_series/formal_power_series.pow.test.cpp": "2023-02-06 14:16:07 +0900",
"tests/graph/bellman_ford.test.cpp": "2023-02-06 14:16:07 +0900",
"tests/graph/dijkstra.test.cpp": "2023-02-06 14:16:07 +0900",
"tests/graph/floyd_warshall.test.cpp": "2023-02-06 14:16:07 +0900",
"tests/graph/strongly_connected_components.test.cpp": "2023-02-06 14:16:07 +0900",
"tests/graph/tree/centroid_decomposition.test.cpp": "2023-02-06 14:16:07 +0900",
"tests/graph/tree/diameter.test.cpp": "2023-02-06 14:16:07 +0900",
"tests/graph/tree/heavy_light_decomposition.test.cpp": "2023-02-06 14:16:07 +0900",
"tests/graph/tree/least_common_ancestor.test.cpp": "2023-02-06 14:16:07 +0900",
"tests/graph/tree/level_ancestor.lca.test.cpp": "2023-02-06 14:16:07 +0900",
"tests/graph/tree/level_ancestor.ut.test.cpp": "2023-02-06 14:16:07 +0900",
"tests/linear_algebra/bit_bases.test.cpp": "2023-02-06 14:16:07 +0900",
"tests/linear_algebra/bit_bases.ut.test.cpp": "2023-02-06 14:16:07 +0900",
"tests/linear_algebra/dynamic_matrix.test.cpp": "2023-02-06 14:16:07 +0900",
"tests/linear_algebra/int_bases.test.cpp": "2023-02-06 14:16:07 +0900",
"tests/linear_algebra/int_bases.ut.test.cpp": "2023-02-06 14:16:07 +0900",
"tests/linear_algebra/static_matrix.test.cpp": "2023-02-06 14:16:07 +0900",
"tests/number/divisors.test.cpp": "2023-02-06 14:16:07 +0900",
"tests/number/mod_nthroot.test.cpp": "2023-02-06 14:56:25 +0900",
"tests/number/mod_sqrt.test.cpp": "2023-02-06 14:16:07 +0900",
"tests/number/multiplicative_prefix_sum.totient.test.cpp": "2023-02-06 14:16:07 +0900",
"tests/number/prime_factors.test.cpp": "2023-02-06 14:56:25 +0900",
"tests/number/prime_powersum.primecount.test.cpp": "2023-02-06 14:16:07 +0900",
"tests/numerical/convolution.ut.test.cpp": "2023-02-06 14:16:07 +0900",
"tests/set_power_series/and_convolution.test.cpp": "2023-02-06 14:16:07 +0900",
"tests/set_power_series/or_convolution.test.cpp": "2023-02-06 14:16:07 +0900",
"tests/set_power_series/subset_convolution.test.cpp": "2023-02-06 14:16:07 +0900",
"tests/set_power_series/xor_convolution.test.cpp": "2023-02-06 14:16:07 +0900",
"tests/string/manacher.test.cpp": "2023-02-06 14:41:51 +0900",
"tests/string/morris_pratt.ut.test.cpp": "2023-02-06 14:41:51 +0900",
"tests/string/suffix_array.test.cpp": "2023-02-06 14:16:07 +0900",
"tests/string/z_algorithm.test.cpp": "2023-02-06 14:41:51 +0900",
"tests/util/int_nthroot.test.cpp": "2023-02-06 14:16:07 +0900",
"tests/util/io.test.cpp": "2023-02-06 14:16:07 +0900",
"tests/util/nd_rep.ut.test.cpp": "2023-02-06 14:16:07 +0900",
"tests/util/nd_vec.ut.test.cpp": "2023-02-06 14:16:07 +0900",
"tests/util/printer.ut.test.cpp": "2023-02-06 14:16:07 +0900",
"tests/util/rng.ut.test.cpp": "2023-02-06 14:16:07 +0900",
"tests/util/scanner.ut.test.cpp": "2023-02-06 14:16:07 +0900",
"tests/util/stopwatch.ut.test.cpp": "2023-02-06 14:16:07 +0900",
"tests/util/zipper.ut.test.cpp": "2023-02-06 14:16:07 +0900"
}